hydrophobicity_explorer/MakePolymer.py
hydrophobicity_explorer/__init__.py
hydrophobicity_explorer/custom_input_to_mol_file.py
hydrophobicity_explorer/nb.py
hydrophobicity_explorer/random_polymer_to_mol_file.py
hydrophobicity_explorer/settings.py
hydrophobicity_explorer/smiles.py
hydrophobicity_explorer-0.1.4.0.dist-info/METADATA
hydrophobicity_explorer-0.1.4.0.dist-info/WHEEL
hydrophobicity_explorer-0.1.4.0.dist-info/entry_points.txt
hydrophobicity_explorer-0.1.4.0.dist-info/top_level.txt
hydrophobicity_explorer-0.1.4.0.dist-info/RECORD
