Metadata-Version: 2.1
Name: hydrophobicity-explorer
Version: 0.1.4.0
Summary: Facilitates solubility calculations on a wide range of polymers.
Home-page: https://github.com/TheHydrophobicityProject/HydrophobicityExplorer
Author: Sander Cohen-Janes
Author-email: sander.cohen-janes@yale.edu
Classifier: Programming Language :: Python
Classifier: Programming Language :: Python :: 3
Classifier: Programming Language :: Python :: 3.6
Requires-Dist: rdkit
Requires-Dist: scipy
Requires-Dist: pandas
Requires-Dist: matplotlib
Requires-Dist: rich
